_pyink_version.py
pyink/__init__.py
pyink/__main__.py
pyink/_width_table.py
pyink/brackets.py
pyink/cache.py
pyink/comments.py
pyink/concurrency.py
pyink/const.py
pyink/debug.py
pyink/files.py
pyink/handle_ipynb_magics.py
pyink/ink.py
pyink/ink_adjusted_lines.py
pyink/ink_comments.py
pyink/linegen.py
pyink/lines.py
pyink/mode.py
pyink/nodes.py
pyink/numerics.py
pyink/output.py
pyink/parsing.py
pyink/py.typed
pyink/ranges.py
pyink/report.py
pyink/rusty.py
pyink/schema.py
pyink/strings.py
pyink/trans.py
pyink/resources/__init__.py
pyink/resources/pyink.schema.json
pyink-24.10.1.dist-info/METADATA
pyink-24.10.1.dist-info/WHEEL
pyink-24.10.1.dist-info/entry_points.txt
pyink-24.10.1.dist-info/licenses/LICENSE
pyink-24.10.1.dist-info/RECORD
